basegun_ml/CNNIQA.pth
basegun_ml/__init__.py
basegun_ml/card_detection.onnx
basegun_ml/classification.pt
basegun_ml/classification.py
basegun_ml/exceptions.py
basegun_ml/keypoints.pt
basegun_ml/measure.py
basegun_ml/ocr.py
basegun_ml/utils.py
basegun_ml/warmup.jpg
basegun_ml/PaddleModels/classification/inference.pdiparams
basegun_ml/PaddleModels/classification/inference.pdiparams.info
basegun_ml/PaddleModels/classification/inference.pdmodel
basegun_ml/PaddleModels/detection/inference.pdiparams
basegun_ml/PaddleModels/detection/inference.pdiparams.info
basegun_ml/PaddleModels/detection/inference.pdmodel
basegun_ml/PaddleModels/recognition/inference.pdiparams
basegun_ml/PaddleModels/recognition/inference.pdiparams.info
basegun_ml/PaddleModels/recognition/inference.pdmodel
basegun_ml-2.0.5.dist-info/LICENSE
basegun_ml-2.0.5.dist-info/METADATA
basegun_ml-2.0.5.dist-info/WHEEL
basegun_ml-2.0.5.dist-info/top_level.txt
basegun_ml-2.0.5.dist-info/RECORD
