Metadata-Version: 2.1
Name: basegun_ml
Version: 2.0.5
Summary: A deeplearning package for the basegun weapon recognition app
Author: aurelien martinez
License: GNU AFFERO GENERAL PUBLIC LICENSE
Project-URL: Basegun-ml, https://github.com/datalab-mi/Basegun-ml
Project-URL: Basegun, https://github.com/datalab-mi/Basegun
Classifier: Programming Language :: Python :: 3
Classifier: Operating System :: OS Independent
Requires-Python: >=3.8
License-File: LICENSE
Requires-Dist: ultralytics >=8.2.48
Requires-Dist: pillow >=7.1.2
Requires-Dist: onnxruntime >=1.9.0
Requires-Dist: opencv-python >=4.6.0
Requires-Dist: numpy >=1.21.6
Requires-Dist: fuzzysearch >=0.7.3
Requires-Dist: pyiqa ==0.1.11
Requires-Dist: torch ==2.3.1
Requires-Dist: paddleocr ==2.7.3
Requires-Dist: paddlepaddle ==3.0.0b1
